README.md
setup.cfg
setup.py
sports_plotter/__init__.py
sports_plotter/examples.py
sports_plotter/hockey.py
sports_plotter/soccer.py
sports_plotter.egg-info/PKG-INFO
sports_plotter.egg-info/SOURCES.txt
sports_plotter.egg-info/dependency_links.txt
sports_plotter.egg-info/not-zip-safe
sports_plotter.egg-info/requires.txt
sports_plotter.egg-info/top_level.txt