Metadata-Version: 1.1
Name: sports-plotter
Version: 1.3
Summary: package making it easier to plot on soccer pitches and hockey rinks
Home-page: https://github.com/delara38/sports_plotter
Author: Nathan de Lara
Author-email: natan.de.lara@gmail.com
License: MIT
Download-URL: https://github.com/delara38/sports_plotter/archive/1.3.tar.gz
Platform: UNKNOWN
